<?xml version="1.0" encoding="utf-8"?>
<TextureAtlas imagePath="secret history mario.png">
	<!-- Created with Adobe Animate version 21.0.2.37893 -->
	<!-- http://www.adobe.com/products/animate.html -->
	<SubTexture name="dictator mario down0000" x="0" y="0" width="345" height="547" frameX="-30" frameY="0" frameWidth="375" frameHeight="547"/>
	<SubTexture name="dictator mario down0001" x="345" y="0" width="353" height="547" frameX="-22" frameY="0" frameWidth="375" frameHeight="547"/>
	<SubTexture name="dictator mario down0002" x="698" y="0" width="355" height="546" frameX="-15" frameY="-1" frameWidth="375" frameHeight="547"/>
	<SubTexture name="dictator mario down0003" x="1053" y="0" width="363" height="546" frameX="-7" frameY="-1" frameWidth="375" frameHeight="547"/>
	<SubTexture name="dictator mario down0004" x="1416" y="0" width="368" height="546" frameX="0" frameY="-1" frameWidth="375" frameHeight="547"/>
	<SubTexture name="dictator mario idle0000" x="1784" y="0" width="272" height="593" frameX="-32" frameY="-3" frameWidth="318" frameHeight="596"/>
	<SubTexture name="dictator mario idle0001" x="2056" y="0" width="280" height="594" frameX="-24" frameY="-2" frameWidth="318" frameHeight="596"/>
	<SubTexture name="dictator mario idle0002" x="2336" y="0" width="282" height="595" frameX="-17" frameY="-1" frameWidth="318" frameHeight="596"/>
	<SubTexture name="dictator mario idle0003" x="2618" y="0" width="291" height="595" frameX="-8" frameY="-1" frameWidth="318" frameHeight="596"/>
	<SubTexture name="dictator mario idle0004" x="2909" y="0" width="314" height="595" frameX="0" frameY="0" frameWidth="318" frameHeight="596"/>
	<SubTexture name="dictator mario idle0005" x="3223" y="0" width="306" height="595" frameX="-8" frameY="-1" frameWidth="318" frameHeight="596"/>
	<SubTexture name="dictator mario idle0006" x="3529" y="0" width="302" height="595" frameX="-16" frameY="-1" frameWidth="318" frameHeight="596"/>
	<SubTexture name="dictator mario idle0007" x="0" y="595" width="294" height="594" frameX="-24" frameY="-2" frameWidth="318" frameHeight="596"/>
	<SubTexture name="dictator mario idle0008" x="294" y="595" width="270" height="593" frameX="-32" frameY="-3" frameWidth="318" frameHeight="596"/>
	<SubTexture name="dictator mario idle0009" x="294" y="595" width="270" height="593" frameX="-32" frameY="-3" frameWidth="318" frameHeight="596"/>
	<SubTexture name="dictator mario idle0010" x="564" y="595" width="264" height="593" frameX="-32" frameY="-3" frameWidth="318" frameHeight="596"/>
	<SubTexture name="dictator mario left0000" x="828" y="595" width="358" height="593" frameX="-16" frameY="-1" frameWidth="377" frameHeight="594"/>
	<SubTexture name="dictator mario left0001" x="1186" y="595" width="364" height="593" frameX="-10" frameY="-1" frameWidth="377" frameHeight="594"/>
	<SubTexture name="dictator mario left0002" x="1550" y="595" width="370" height="593" frameX="-5" frameY="-1" frameWidth="377" frameHeight="594"/>
	<SubTexture name="dictator mario left0003" x="1920" y="595" width="377" height="594"/>
	<SubTexture name="dictator mario left0004" x="2297" y="595" width="377" height="594"/>
	<SubTexture name="dictator mario left0005" x="2297" y="595" width="377" height="594"/>
	<SubTexture name="dictator mario left0006" x="2674" y="595" width="377" height="594"/>
	<SubTexture name="dictator mario left0007" x="2674" y="595" width="377" height="594"/>
	<SubTexture name="dictator mario left0008" x="3051" y="595" width="377" height="594"/>
	<SubTexture name="dictator mario left0009" x="3051" y="595" width="377" height="594"/>
	<SubTexture name="dictator mario right0000" x="3428" y="595" width="427" height="576" frameX="-29" frameY="0" frameWidth="456" frameHeight="576"/>
	<SubTexture name="dictator mario right0001" x="0" y="1189" width="434" height="575" frameX="-22" frameY="-1" frameWidth="456" frameHeight="576"/>
	<SubTexture name="dictator mario right0002" x="434" y="1189" width="442" height="574" frameX="-14" frameY="-2" frameWidth="456" frameHeight="576"/>
	<SubTexture name="dictator mario right0003" x="876" y="1189" width="449" height="573" frameX="-7" frameY="-3" frameWidth="456" frameHeight="576"/>
	<SubTexture name="dictator mario right0004" x="1325" y="1189" width="431" height="573" frameX="0" frameY="-3" frameWidth="456" frameHeight="576"/>
	<SubTexture name="dictator mario right0005" x="1325" y="1189" width="431" height="573" frameX="0" frameY="-3" frameWidth="456" frameHeight="576"/>
	<SubTexture name="dictator mario right0006" x="1756" y="1189" width="437" height="573" frameX="0" frameY="-3" frameWidth="456" frameHeight="576"/>
	<SubTexture name="dictator mario right0007" x="1756" y="1189" width="437" height="573" frameX="0" frameY="-3" frameWidth="456" frameHeight="576"/>
	<SubTexture name="dictator mario right0008" x="2193" y="1189" width="427" height="573" frameX="0" frameY="-3" frameWidth="456" frameHeight="576"/>
	<SubTexture name="dictator mario right0009" x="2193" y="1189" width="427" height="573" frameX="0" frameY="-3" frameWidth="456" frameHeight="576"/>
	<SubTexture name="dictator mario up0000" x="2620" y="1189" width="277" height="591" frameX="-14" frameY="0" frameWidth="308" frameHeight="593"/>
	<SubTexture name="dictator mario up0001" x="2897" y="1189" width="284" height="591" frameX="-10" frameY="-1" frameWidth="308" frameHeight="593"/>
	<SubTexture name="dictator mario up0002" x="3181" y="1189" width="290" height="591" frameX="-7" frameY="-1" frameWidth="308" frameHeight="593"/>
	<SubTexture name="dictator mario up0003" x="3471" y="1189" width="298" height="591" frameX="-3" frameY="-2" frameWidth="308" frameHeight="593"/>
	<SubTexture name="dictator mario up0004" x="3769" y="1189" width="308" height="590" frameX="0" frameY="-3" frameWidth="308" frameHeight="593"/>
</TextureAtlas>
